deepspeech_cli/__init__.py
deepspeech_cli/config.py
deepspeech_cli/deepspeech_cli.py
deepspeech_cli-0.2.3.dist-info/entry_points.txt
deepspeech_cli-0.2.3.dist-info/LICENSE
deepspeech_cli-0.2.3.dist-info/WHEEL
deepspeech_cli-0.2.3.dist-info/METADATA
deepspeech_cli-0.2.3.dist-info/RECORD
