Metadata-Version: 2.1
Name: deepspeech-cli
Version: 0.2.3
Summary: 
Home-page: https://github.com/tddschn/deepspeech-cli
License: MIT
Keywords: git,asyncio
Author: Xinyuan Chen
Author-email: 45612704+tddschn@users.noreply.github.com
Requires-Python: >=3.10,<4.0
Classifier: License :: OSI Approved :: MIT License
Classifier: Programming Language :: Python :: 3
Classifier: Programming Language :: Python :: 3.10
Requires-Dist: typer (>=0.4.1,<0.5.0)
Project-URL: Bug Tracker, https://github.com/tddschn/deepspeech-cli/issues
Project-URL: Repository, https://github.com/tddschn/deepspeech-cli
